{
   "cid_to_cname": {
      "5": "gaming",
      "0": "toner_online",
      "1": "travel",
      "2": "car_parts",
      "3": "online_tickets",
      "4": "food_delivery"
   },
   "cname_to_cid": {
      "car_parts": 2,
      "food_delivery": 4,
      "gaming": 5,
      "online_tickets": 3,
      "toner_online": 0,
      "travel": 1
   },
   "did_to_dname": {
      "82": "ilumnia",
      "83": "homerj",
      "84": "gamepro",
      "85": "spieletipps",
      "86": "playnation",
      "87": "gamona",
      "88": "gamerant",
      "89": "mein-mmo",
      "90": "twoplayergames",
      "91": "gamingwonderland",
      "92": "gamerfanatics",
      "93": "rpforum",
      "94": "areagames",
      "95": "gamezone",
      "96": "jeuxactu",
      "97": "onlinewelten",
      "98": "wowhead",
      "99": "zeldadungeon",
      "100": "lolking",
      "101": "gamergossip",
      "102": "dotabuff",
      "103": "squaretimes",
      "104": "gameforum",
      "105": "gta5-mods",
      "106": "playreactive",
      "107": "ps4-magazin",
      "108": "mmozone",
      "109": "gronkh",
      "110": "kotaku",
      "111": "gamingnewstime",
      "112": "extreme-gaming",
      "113": "counter-strike",
      "114": "pietsmiet",
      "115": "gamesgames",
      "116": "ign",
      "117": "4players",
      "118": "playmassive",
      "119": "giga",
      "120": "aeriagames",
      "121": "gamer-site",
      "122": "dota2",
      "123": "gameinformer",
      "124": "leaguecraft",
      "125": "mmo-champion",
      "126": "consolegameswiki",
      "127": "gamebanshee",
      "128": "gamestar",
      "129": "pcgames",
      "130": "spielemagazin",
      "131": "gamersnews",
      "132": "dota2lounge",
      "133": "pcgameshardware",
      "134": "leagueoflegends",
      "135": "psinside",
      "136": "finalfantasyxiv",
      "137": "xbox360-forum",
      "138": "gamefaqs",
      "139": "final-fantasy",
      "140": "dotafire",
      "141": "gamingstime",
      "142": "buffed",
      "143": "kotakgame",
      "144": "eurogamer",
      "145": "ingame",
      "146": "ps4news",
      "147": "maniac",
      "148": "lolskill",
      "149": "pcgamer",
      "150": "gamesradar",
      "151": "gamefront",
      "152": "gamesaktuell",
      "153": "shockwave",
      "154": "consolewars",
      "155": "games",
      "156": "gamespot",
      "157": "diablofans",
      "158": "gameformats",
      "159": "gamersglobal",
      "160": "gta-5-forum",
      "161": "jpgames",
      "162": "gamesandthings",
      "163": "gtainside",
      "164": "ffxiv-freetrial",
      "0": "bueromarkt-ag",
      "1": "druckerzubehoer",
      "10": "ihrtonershop",
      "11": "druckerpatronenhandel",
      "12": "tintenalarm",
      "13": "tinte24",
      "14": "qraex",
      "15": "tintenfix",
      "16": "tonerdumping",
      "17": "booking",
      "18": "ab-in-den-urlaub",
      "19": "trivago",
      "2": "schaefer-shop",
      "20": "check24",
      "21": "tripadvisor",
      "22": "ab-in-den-urlaub-deals",
      "23": "hotel",
      "24": "hotelreservierung",
      "25": "hotels",
      "26": "travel24",
      "27": "reisen",
      "28": "ferienknaller",
      "29": "holidaycheck",
      "3": "hq-patronen",
      "30": "ab-ins-blaue",
      "31": "travel24-hotels",
      "32": "spar-mit",
      "33": "travelcircus",
      "34": "mister-auto",
      "35": "atp-autoteile",
      "36": "kfzteile",
      "37": "pkwteile",
      "38": "autoteiledirekt",
      "39": "autodoc",
      "4": "tintencenter",
      "40": "autoteile-teufel",
      "41": "daparto",
      "42": "partacus",
      "43": "bremsen",
      "44": "autoteile-guenstig",
      "45": "autoteile24",
      "46": "teile-direkt",
      "47": "bandel-online",
      "48": "autoteilebilliger",
      "49": "der-ersatzteile-profi",
      "5": "hd-toner",
      "50": "ersatzteile-info",
      "51": "teilando",
      "52": "austroteile",
      "53": "kfzteile123",
      "54": "bartebben",
      "55": "eventim",
      "56": "viagogo",
      "57": "ticketonline",
      "58": "stubhub",
      "59": "musicals",
      "6": "druckerpatronen",
      "60": "global-tickets",
      "61": "ticketbis",
      "62": "prestigetickets",
      "63": "laolaevents",
      "64": "ticketbande",
      "65": "koelnticket",
      "66": "tickettube",
      "67": "tickets75",
      "68": "safetickets",
      "69": "musicalkaufhaus",
      "7": "die-patrone",
      "70": "musicalpaket",
      "71": "lieferando",
      "72": "lieferheld",
      "73": "pizza",
      "74": "lieferservice",
      "75": "deliveroo",
      "76": "online-pizza",
      "77": "foodora",
      "78": "resto-in",
      "79": "bringbutler",
      "8": "gubidu",
      "80": "egourmery",
      "81": "pizzeria",
      "9": "dertoner"
   },
   "dname_to_cid": {
      "4players": 5,
      "ab-in-den-urlaub": 1,
      "ab-in-den-urlaub-deals": 1,
      "ab-ins-blaue": 1,
      "aeriagames": 5,
      "areagames": 5,
      "atp-autoteile": 2,
      "austroteile": 2,
      "autodoc": 2,
      "autoteile-guenstig": 2,
      "autoteile-teufel": 2,
      "autoteile24": 2,
      "autoteilebilliger": 2,
      "autoteiledirekt": 2,
      "bandel-online": 2,
      "bartebben": 2,
      "booking": 1,
      "bremsen": 2,
      "bringbutler": 4,
      "bueromarkt-ag": 0,
      "buffed": 5,
      "check24": 1,
      "consolegameswiki": 5,
      "consolewars": 5,
      "counter-strike": 5,
      "daparto": 2,
      "deliveroo": 4,
      "der-ersatzteile-profi": 2,
      "dertoner": 0,
      "diablofans": 5,
      "die-patrone": 0,
      "dota2": 5,
      "dota2lounge": 5,
      "dotabuff": 5,
      "dotafire": 5,
      "druckerpatronen": 0,
      "druckerpatronenhandel": 0,
      "druckerzubehoer": 0,
      "egourmery": 4,
      "ersatzteile-info": 2,
      "eurogamer": 5,
      "eventim": 3,
      "extreme-gaming": 5,
      "ferienknaller": 1,
      "final-fantasy": 5,
      "finalfantasyxiv": 5,
      "foodora": 4,
      "gamebanshee": 5,
      "gamefaqs": 5,
      "gameformats": 5,
      "gameforum": 5,
      "gamefront": 5,
      "gameinformer": 5,
      "gamepro": 5,
      "gamer-site": 5,
      "gamerant": 5,
      "gamerfanatics": 5,
      "gamergossip": 5,
      "gamersglobal": 5,
      "gamersnews": 5,
      "games": 5,
      "gamesaktuell": 5,
      "gamesandthings": 5,
      "gamesgames": 5,
      "gamespot": 5,
      "gamesradar": 5,
      "gamestar": 5,
      "gamezone": 5,
      "gamingnewstime": 5,
      "gamingstime": 5,
      "gamingwonderland": 5,
      "gamona": 5,
      "giga": 5,
      "global-tickets": 3,
      "gronkh": 5,
      "gta-5-forum": 5,
      "gta5-mods": 5,
      "gtainside": 5,
      "gubidu": 0,
      "hd-toner": 0,
      "holidaycheck": 1,
      "homerj": 5,
      "hotel": 1,
      "hotelreservierung": 1,
      "hotels": 1,
      "hq-patronen": 0,
      "ign": 5,
      "ihrtonershop": 0,
      "ilumnia": 5,
      "ingame": 5,
      "jeuxactu": 5,
      "jpgames": 5,
      "kfzteile": 2,
      "kfzteile123": 2,
      "koelnticket": 3,
      "kotakgame": 5,
      "kotaku": 5,
      "laolaevents": 3,
      "leaguecraft": 5,
      "leagueoflegends": 5,
      "lieferando": 4,
      "lieferheld": 4,
      "lieferservice": 4,
      "lolking": 5,
      "lolskill": 5,
      "maniac": 5,
      "mein-mmo": 5,
      "mister-auto": 2,
      "mmo-champion": 5,
      "mmozone": 5,
      "musicalkaufhaus": 3,
      "musicalpaket": 3,
      "musicals": 3,
      "online-pizza": 4,
      "onlinewelten": 5,
      "partacus": 2,
      "pcgamer": 5,
      "pcgames": 5,
      "pcgameshardware": 5,
      "pietsmiet": 5,
      "pizza": 4,
      "pizzeria": 4,
      "pkwteile": 2,
      "playmassive": 5,
      "playnation": 5,
      "playreactive": 5,
      "prestigetickets": 3,
      "ps4-magazin": 5,
      "ps4news": 5,
      "psinside": 5,
      "qraex": 0,
      "reisen": 1,
      "resto-in": 4,
      "rpforum": 5,
      "safetickets": 3,
      "schaefer-shop": 0,
      "shockwave": 5,
      "spar-mit": 1,
      "spielemagazin": 5,
      "spieletipps": 5,
      "squaretimes": 5,
      "stubhub": 3,
      "teilando": 2,
      "teile-direkt": 2,
      "ticketbande": 3,
      "ticketbis": 3,
      "ticketonline": 3,
      "tickets75": 3,
      "tickettube": 3,
      "tinte24": 0,
      "tintenalarm": 0,
      "tintencenter": 0,
      "tintenfix": 0,
      "tonerdumping": 0,
      "travel24": 1,
      "travel24-hotels": 1,
      "travelcircus": 1,
      "tripadvisor": 1,
      "trivago": 1,
      "twoplayergames": 5,
      "viagogo": 3,
      "wowhead": 5,
      "xbox360-forum": 5,
      "zeldadungeon": 5,
      "ffxiv-freetrial" : 5
   },
   "dname_to_did": {
      "4players": 117,
      "ab-in-den-urlaub": 18,
      "ab-in-den-urlaub-deals": 22,
      "ab-ins-blaue": 30,
      "aeriagames": 120,
      "areagames": 94,
      "atp-autoteile": 35,
      "austroteile": 52,
      "autodoc": 39,
      "autoteile-guenstig": 44,
      "autoteile-teufel": 40,
      "autoteile24": 45,
      "autoteilebilliger": 48,
      "autoteiledirekt": 38,
      "bandel-online": 47,
      "bartebben": 54,
      "booking": 17,
      "bremsen": 43,
      "bringbutler": 79,
      "bueromarkt-ag": 0,
      "buffed": 142,
      "check24": 20,
      "consolegameswiki": 126,
      "consolewars": 154,
      "counter-strike": 113,
      "daparto": 41,
      "deliveroo": 75,
      "der-ersatzteile-profi": 49,
      "dertoner": 9,
      "diablofans": 157,
      "die-patrone": 7,
      "dota2": 122,
      "dota2lounge": 132,
      "dotabuff": 102,
      "dotafire": 140,
      "druckerpatronen": 6,
      "druckerpatronenhandel": 11,
      "druckerzubehoer": 1,
      "egourmery": 80,
      "ersatzteile-info": 50,
      "eurogamer": 144,
      "eventim": 55,
      "extreme-gaming": 112,
      "ferienknaller": 28,
      "ffxiv-freetrial": 164,
      "final-fantasy": 139,
      "finalfantasyxiv": 136,
      "foodora": 77,
      "gamebanshee": 127,
      "gamefaqs": 138,
      "gameformats": 158,
      "gameforum": 104,
      "gamefront": 151,
      "gameinformer": 123,
      "gamepro": 84,
      "gamer-site": 121,
      "gamerant": 88,
      "gamerfanatics": 92,
      "gamergossip": 101,
      "gamersglobal": 159,
      "gamersnews": 131,
      "games": 155,
      "gamesaktuell": 152,
      "gamesandthings": 162,
      "gamesgames": 115,
      "gamespot": 156,
      "gamesradar": 150,
      "gamestar": 128,
      "gamezone": 95,
      "gamingnewstime": 111,
      "gamingstime": 141,
      "gamingwonderland": 91,
      "gamona": 87,
      "giga": 119,
      "global-tickets": 60,
      "gronkh": 109,
      "gta-5-forum": 160,
      "gta5-mods": 105,
      "gtainside": 163,
      "gubidu": 8,
      "hd-toner": 5,
      "holidaycheck": 29,
      "homerj": 83,
      "hotel": 23,
      "hotelreservierung": 24,
      "hotels": 25,
      "hq-patronen": 3,
      "ign": 116,
      "ihrtonershop": 10,
      "ilumnia": 82,
      "ingame": 145,
      "jeuxactu": 96,
      "jpgames": 161,
      "kfzteile": 36,
      "kfzteile123": 53,
      "koelnticket": 65,
      "kotakgame": 143,
      "kotaku": 110,
      "laolaevents": 63,
      "leaguecraft": 124,
      "leagueoflegends": 134,
      "lieferando": 71,
      "lieferheld": 72,
      "lieferservice": 74,
      "lolking": 100,
      "lolskill": 148,
      "maniac": 147,
      "mein-mmo": 89,
      "mister-auto": 34,
      "mmo-champion": 125,
      "mmozone": 108,
      "musicalkaufhaus": 69,
      "musicalpaket": 70,
      "musicals": 59,
      "online-pizza": 76,
      "onlinewelten": 97,
      "partacus": 42,
      "pcgamer": 149,
      "pcgames": 129,
      "pcgameshardware": 133,
      "pietsmiet": 114,
      "pizza": 73,
      "pizzeria": 81,
      "pkwteile": 37,
      "playmassive": 118,
      "playnation": 86,
      "playreactive": 106,
      "prestigetickets": 62,
      "ps4-magazin": 107,
      "ps4news": 146,
      "psinside": 135,
      "qraex": 14,
      "reisen": 27,
      "resto-in": 78,
      "rpforum": 93,
      "safetickets": 68,
      "schaefer-shop": 2,
      "shockwave": 153,
      "spar-mit": 32,
      "spielemagazin": 130,
      "spieletipps": 85,
      "squaretimes": 103,
      "stubhub": 58,
      "teilando": 51,
      "teile-direkt": 46,
      "ticketbande": 64,
      "ticketbis": 61,
      "ticketonline": 57,
      "tickets75": 67,
      "tickettube": 66,
      "tinte24": 13,
      "tintenalarm": 12,
      "tintencenter": 4,
      "tintenfix": 15,
      "tonerdumping": 16,
      "travel24": 26,
      "travel24-hotels": 31,
      "travelcircus": 33,
      "tripadvisor": 21,
      "trivago": 19,
      "twoplayergames": 90,
      "viagogo": 56,
      "wowhead": 98,
      "xbox360-forum": 137,
      "zeldadungeon": 99
   }
}
